aioarp/__about__.py
aioarp/__init__.py
aioarp/_arp.py
aioarp/_async.py
aioarp/_cli.py
aioarp/_client.py
aioarp/_exceptions.py
aioarp/_mock.py
aioarp/_sync.py
aioarp/_utils.py
aioarp/defaults.py
aioarp/_backends/__init__.py
aioarp/_backends/_async.py
aioarp/_backends/_base.py
aioarp/_backends/_mock.py
aioarp/_backends/_sync.py
aioarp-0.0.12.dist-info/METADATA
aioarp-0.0.12.dist-info/WHEEL
aioarp-0.0.12.dist-info/entry_points.txt
aioarp-0.0.12.dist-info/licenses/LICENSE.txt
aioarp-0.0.12.dist-info/RECORD
