Metadata-Version: 2.1
Name: aioarp
Version: 0.0.12
Summary: Aioarp is a ARP protocol implementation that provides synchronous and asynchronous interfaces and gives you complete control over how ARP packets are sent.
Project-URL: Source, https://github.com/karosis88/aioarp
Project-URL: Documentation, https://karosis88.github.io/aioarp/
Project-URL: Changelog, https://github.com/karosis88/aioarp/blob/master/CHANGELOG.md
Project-URL: Issues, https://github.com/karosis88/aioarp/issues
Author-email: Karen Petrosyan <kar.petrosyanpy@gmail.com>
License-Expression: MIT
License-File: LICENSE.txt
Classifier: Development Status :: 4 - Beta
Classifier: Programming Language :: Python
Classifier: Programming Language :: Python :: 3.7
Classifier: Programming Language :: Python :: 3.8
Classifier: Programming Language :: Python :: 3.9
Classifier: Programming Language :: Python :: 3.10
Classifier: Programming Language :: Python :: 3.11
Classifier: Programming Language :: Python :: Implementation :: CPython
Classifier: Programming Language :: Python :: Implementation :: PyPy
Requires-Python: >=3.7
Requires-Dist: anyio==3.6.2
Requires-Dist: getmac==0.9.4
Requires-Dist: typing-extensions==4.6.3
Provides-Extra: cli
Requires-Dist: typer==0.9.0; extra == 'cli'
